onco_cola_utils/__init__.py
onco_cola_utils/advanced_thread_processor/__init__.py
onco_cola_utils/advanced_thread_processor/constants.py
onco_cola_utils/advanced_thread_processor/core.py
onco_cola_utils/advanced_thread_processor/models.py
onco_cola_utils/advanced_thread_processor/README.md
onco_cola_utils/advanced_thread_processor/utils.py
onco_cola_utils/configs/__init__.py
onco_cola_utils/configs/column_strings.py
onco_cola_utils/configs/system.py
onco_cola_utils/default_state/__init__.py
onco_cola_utils/default_state/core.py
onco_cola_utils/default_state/README.md
onco_cola_utils/dual_alphabetic_controller/__init__.py
onco_cola_utils/dual_alphabetic_controller/core.py
onco_cola_utils/file_reader_controller/__init__.py
onco_cola_utils/file_reader_controller/core.py
onco_cola_utils/file_reader_controller/README.md
onco_cola_utils/interrupts/__init__.py
onco_cola_utils/interrupts/core.py
onco_cola_utils/json_reader_controller/__init__.py
onco_cola_utils/json_reader_controller/core.py
onco_cola_utils/json_reader_controller/README.md
onco_cola_utils/key_param_class/__init__.py
onco_cola_utils/key_param_class/core.py
onco_cola_utils/key_param_class/README.md
onco_cola_utils/logger/__init__.py
onco_cola_utils/logger/core.py
onco_cola_utils/logger/README.md
onco_cola_utils/mixin/__init__.py
onco_cola_utils/mixin/debug_mixin/__init__.py
onco_cola_utils/mixin/debug_mixin/core.py
onco_cola_utils/pretty_print/__init__.py
onco_cola_utils/pretty_print/core.py
onco_cola_utils/pretty_print/README.md
onco_cola_utils/progress_message/__init__.py
onco_cola_utils/progress_message/core.py
onco_cola_utils/progress_message/README.md
onco_cola_utils/reader_controller/__init__.py
onco_cola_utils/reader_controller/core.py
onco_cola_utils/reader_controller/exceptions.py
onco_cola_utils/reader_controller/README.md
onco_cola_utils/reader_controller/types.py
onco_cola_utils/tools/__init__.py
onco_cola_utils/tools/core.py
onco_cola_utils/tools/README.md
onco_cola_utils-0.7.2.dist-info/licenses/LICENSE
onco_cola_utils-0.7.2.dist-info/METADATA
onco_cola_utils-0.7.2.dist-info/WHEEL
onco_cola_utils-0.7.2.dist-info/RECORD
