Metadata-Version: 2.4
Name: onco-cola-utils
Version: 0.7.2
Summary: Мой сборник различных утилит для работы с файлами
License: MIT
License-File: LICENSE
Keywords: utils,excel,pandas,tools,openpyxl,key-param,key-value
Author: Volodin Alexandr Sergeevich
Author-email: endocrinologist@ya.ru
Requires-Python: >=3.9,<4.0
Classifier: License :: OSI Approved :: MIT License
Classifier: Operating System :: OS Independent
Classifier: Programming Language :: Python :: 3
Classifier: Programming Language :: Python :: 3.9
Classifier: Programming Language :: Python :: 3.10
Classifier: Programming Language :: Python :: 3.11
Classifier: Programming Language :: Python :: 3.12
Classifier: Programming Language :: Python :: 3.13
Classifier: Programming Language :: Python :: 3.14
Requires-Dist: build (>=1.3.0)
Requires-Dist: deprecated (>=1.2)
Requires-Dist: loguru (>=0.7.3,<0.8.0)
Requires-Dist: openpyxl (>=3.0)
Requires-Dist: pandas (>=1.5)
Requires-Dist: tiktoken (>=0.11.0)
Requires-Dist: twine (>=6.1.0)
Project-URL: Homepage, https://t.me/hitomamoru
Project-URL: Repository, https://github.com/VolodinAS/onco-cola-tools
